_rapids_dask_dependency.pth
rapids_dask_dependency/__init__.py
rapids_dask_dependency/dask_loader.py
rapids_dask_dependency/loaders.py
rapids_dask_dependency/utils.py
rapids_dask_dependency/patches/__init__.py
rapids_dask_dependency/patches/dask/__init__.py
rapids_dask_dependency/patches/distributed/__init__.py
rapids_dask_dependency-25.12.1.dist-info/licenses/LICENSE
rapids_dask_dependency-25.12.1.dist-info/METADATA
rapids_dask_dependency-25.12.1.dist-info/WHEEL
rapids_dask_dependency-25.12.1.dist-info/top_level.txt
rapids_dask_dependency-25.12.1.dist-info/RECORD
