Metadata-Version: 2.4
Name: rapids-dask-dependency
Version: 25.12.1
Summary: Dask and Distributed version pinning for RAPIDS
License: Apache-2.0
License-File: LICENSE
Requires-Dist: dask==2025.9.2
Requires-Dist: distributed==2025.9.2
Provides-Extra: test
Requires-Dist: pytest; extra == "test"
Dynamic: license-file
